README.rst
setup.py
bin/caesarcipher
caesarcipher/__init__.py
caesarcipher/caesarcipher.py
caesarcipher/cmdline.py
caesarcipher.egg-info/PKG-INFO
caesarcipher.egg-info/SOURCES.txt
caesarcipher.egg-info/dependency_links.txt
caesarcipher.egg-info/top_level.txt
tests/test_caesarcipher.py