Metadata-Version: 1.1
Name: caesarcipher
Version: 1.0
Summary: A Python package and command line script for encoding, decoding and cracking Caesar ciphers.
Home-page: https://github.com/RobSpectre/Caesar-Cipher
Author: Rob Spectre
Author-email: rob@brooklynhacker.com
License: MIT
Platform: UNKNOWN
Classifier: Programming Language :: Python
Classifier: Programming Language :: Python :: 2
Classifier: Programming Language :: Python :: 3
Classifier: License :: OSI Approved :: MIT License
Classifier: Operating System :: OS Independent
Classifier: Development Status :: 5 - Production/Stable
Classifier: Intended Audience :: Developers
Classifier: Natural Language :: English
Classifier: Environment :: Console
Classifier: Topic :: Security :: Cryptography
